donna/__init__.py
donna/artifacts/__init__.py
donna/artifacts/usage/__init__.py
donna/artifacts/usage/artifacts.md
donna/artifacts/usage/cli.md
donna/artifacts/usage/worlds.md
donna/artifacts/work/__init__.py
donna/artifacts/work/do_it.md
donna/artifacts/work/do_it_fast.md
donna/artifacts/work/planning.md
donna/cli/__init__.py
donna/cli/__main__.py
donna/cli/application.py
donna/cli/commands/__init__.py
donna/cli/commands/artifacts.py
donna/cli/commands/projects.py
donna/cli/commands/sessions.py
donna/cli/types.py
donna/cli/utils.py
donna/core/__init__.py
donna/core/entities.py
donna/core/errors.py
donna/core/result.py
donna/core/utils.py
donna/domain/__init__.py
donna/domain/errors.py
donna/domain/ids.py
donna/lib/__init__.py
donna/lib/sources.py
donna/lib/worlds.py
donna/machine/__init__.py
donna/machine/action_requests.py
donna/machine/artifacts.py
donna/machine/changes.py
donna/machine/errors.py
donna/machine/operations.py
donna/machine/primitives.py
donna/machine/sessions.py
donna/machine/state.py
donna/machine/tasks.py
donna/machine/templates.py
donna/primitives/__init__.py
donna/primitives/artifacts/__init__.py
donna/primitives/artifacts/specification.py
donna/primitives/artifacts/workflow.py
donna/primitives/directives/__init__.py
donna/primitives/directives/goto.py
donna/primitives/directives/task_variable.py
donna/primitives/directives/view.py
donna/primitives/operations/__init__.py
donna/primitives/operations/finish_workflow.py
donna/primitives/operations/request_action.py
donna/primitives/operations/run_script.py
donna/protocol/__init__.py
donna/protocol/cell_shortcuts.py
donna/protocol/cells.py
donna/protocol/errors.py
donna/protocol/formatters/__init__.py
donna/protocol/formatters/automation.py
donna/protocol/formatters/base.py
donna/protocol/formatters/human.py
donna/protocol/formatters/llm.py
donna/protocol/modes.py
donna/protocol/nodes.py
donna/world/__init__.py
donna/world/artifacts.py
donna/world/artifacts_discovery.py
donna/world/config.py
donna-0.2.0.dist-info/METADATA
donna-0.2.0.dist-info/WHEEL
donna-0.2.0.dist-info/entry_points.txt
donna-0.2.0.dist-info/licenses/LICENSE
donna-0.2.0.dist-info/RECORD
