Metadata-Version: 2.4
Name: donna
Version: 0.2.0
Summary: A deterministic workflow and state orchestration engine for LLM agents.
License-Expression: BSD-3-Clause
License-File: LICENSE
Keywords: ai,agent,cli,llm,workflow
Author: Aliaksei Yaletski
Author-email: a.eletsky@gmail.com
Requires-Python: >=3.12,<4.0
Classifier: Development Status :: 3 - Alpha
Classifier: Environment :: Console
Classifier: Intended Audience :: Developers
Classifier: Programming Language :: Python :: 3
Classifier: Programming Language :: Python :: 3.12
Classifier: Programming Language :: Python :: 3 :: Only
Classifier: Topic :: Software Development :: Build Tools
Classifier: Topic :: Utilities
Requires-Dist: jinja2 (>=3.1,<3.2)
Requires-Dist: markdown-it-py (>=4.0,<4.1)
Requires-Dist: mdformat (>=1.0.0,<1.1.0)
Requires-Dist: pydantic (>=2.12,<2.13)
Requires-Dist: typer (>=0.20,<0.21)
Project-URL: Homepage, https://github.com/Tiendil/donna
Project-URL: Issues, https://github.com/Tiendil/donna/issues
Project-URL: Repository, https://github.com/Tiendil/donna
